rbpico/__init__.py
rbpico-0.0.1.dist-info/LICENCE.txt
rbpico-0.0.1.dist-info/METADATA
rbpico-0.0.1.dist-info/WHEEL
rbpico-0.0.1.dist-info/top_level.txt
rbpico-0.0.1.dist-info/RECORD
